bucketflow/__init__.py
bucketflow/async_token_bucket.py
bucketflow/decorators.py
bucketflow/distributed.py
bucketflow/hierarchical.py
bucketflow/token_bucket.py
bucketflow-0.1.0.dist-info/licenses/LICENSE
bucketflow-0.1.0.dist-info/METADATA
bucketflow-0.1.0.dist-info/WHEEL
bucketflow-0.1.0.dist-info/top_level.txt
bucketflow-0.1.0.dist-info/RECORD
