Metadata-Version: 2.4
Name: bucketflow
Version: 0.1.0
Summary: A Python library for rate limiting using the Token Bucket algorithm
Home-page: https://github.com/innerkore/bucketflow
Author: Gagan (Innerkore)
Author-email: gagan@innerkore.com
License: MIT
Project-URL: Bug Tracker, https://github.com/innerkore/bucketflow/issues
Project-URL: Documentation, https://github.com/innerkore/bucketflow#readme
Project-URL: Source Code, https://github.com/innerkore/bucketflow
Keywords: rate-limiting token-bucket throttling api hierarchical-rate-limiting
Classifier: Development Status :: 4 - Beta
Classifier: Intended Audience :: Developers
Classifier: License :: OSI Approved :: MIT License
Classifier: Operating System :: OS Independent
Classifier: Programming Language :: Python :: 3
Classifier: Programming Language :: Python :: 3.6
Classifier: Programming Language :: Python :: 3.7
Classifier: Programming Language :: Python :: 3.8
Classifier: Programming Language :: Python :: 3.9
Classifier: Programming Language :: Python :: 3.10
Classifier: Topic :: Software Development :: Libraries :: Python Modules
Classifier: Topic :: System :: Networking
Requires-Python: >=3.6
License-File: LICENSE
Provides-Extra: distributed
Requires-Dist: redis>=3.0.0; extra == "distributed"
Provides-Extra: dev
Requires-Dist: pytest>=6.0.0; extra == "dev"
Requires-Dist: pytest-cov>=2.10.0; extra == "dev"
Requires-Dist: black>=20.8b1; extra == "dev"
Requires-Dist: flake8>=3.8.0; extra == "dev"
Requires-Dist: mypy>=0.800; extra == "dev"
Dynamic: author
Dynamic: author-email
Dynamic: classifier
Dynamic: description
Dynamic: description-content-type
Dynamic: home-page
Dynamic: keywords
Dynamic: license
Dynamic: license-file
Dynamic: project-url
Dynamic: provides-extra
Dynamic: requires-python
Dynamic: summary
